repane/__init__.py
repane/dom.py
repane/expr.py
repane/mesh.py
repane/repane.cp310-win_amd64.pyd
repane-0.1.5.data/data/README/README.md
repane-0.1.5.data/data/licenses/APACHE2
repane-0.1.5.data/data/licenses/MIT
repane-0.1.5.dist-info/LICENSE
repane-0.1.5.dist-info/METADATA
repane-0.1.5.dist-info/WHEEL
repane-0.1.5.dist-info/top_level.txt
repane-0.1.5.dist-info/RECORD
